matan/__init__.py
matan/base.py
matan/files.py
matan/misc.py
matan/fem/tensile/__init__.py
matan/rheology/__init__.py
matan/tensile/__init__.py
matan/tensile/test_module.py
matan/tensile/values.py
matan/tensile/standards/__init__.py
matan/tensile/standards/polymers/ISO527.py
matan/tensile/standards/polymers/__init__.py
matan-0.1.9.dist-info/WHEEL
matan-0.1.9.dist-info/METADATA
matan-0.1.9.dist-info/RECORD
