Metadata-Version: 2.1
Name: matan
Version: 0.1.9
Summary: Material analysis package to plot or extract properties like tensile modulus etc.
Author-email: Igor <igor@its.rel.pl>
Requires-Python: >=3.6
Classifier: Intended Audience :: Science/Research
Classifier: License :: OSI Approved :: GNU General Public License v3 or later (GPLv3+)
Classifier: Topic :: Scientific/Engineering
Classifier: Development Status :: 3 - Alpha
Classifier: Programming Language :: Python :: 3
Requires-Dist: pandas
Project-URL: Documentation, https://matan.codeberg.page/
Project-URL: Source, https://codeberg.org/MatAn/matan
